Pokeam_Base/__init__.py
Pokeam_Base/random_pokemon.py
Pokeam-1.0.0.dist-info/METADATA
Pokeam-1.0.0.dist-info/WHEEL
Pokeam-1.0.0.dist-info/top_level.txt
Pokeam-1.0.0.dist-info/RECORD
